Chozita/Chozita.py
Chozita/__init__.py
Chozita-1.5.7.dist-info/LICENSE
Chozita-1.5.7.dist-info/METADATA
Chozita-1.5.7.dist-info/WHEEL
Chozita-1.5.7.dist-info/top_level.txt
Chozita-1.5.7.dist-info/RECORD
